{"players": [{"account_id": 415493267, "player_slot": 0, "hero_id": 18, "item_0": 182, "item_1": 16, "item_2": 63, "item_3": 11, "item_4": 172, "item_5": 0, "backpack_0": 0, "backpack_1": 0, "backpack_2": 0, "kills": 4, "deaths": 2, "assists": 7, "leaver_status": 0, "last_hits": 42, "denies": 8, "gold_per_min": 349, "xp_per_min": 340, "level": 10, "hero_name": "Sven", "item_0_name": "Stout Shield", "item_1_name": "Iron Branch", "item_2_name": "Power Treads", "item_3_name": "Quelling Blade", "item_4_name": "Mask of Madness", "leaver_status_name": "NONE", "leaver_status_description": "finished match, no abandon"}, {"account_id": 161028509, "player_slot": 1, "hero_id": 2, "item_0": 1, "item_1": 182, "item_2": 12, "item_3": 214, "item_4": 19, "item_5": 46, "backpack_0": 4, "backpack_1": 0, "backpack_2": 0, "kills": 4, "deaths": 1, "assists": 4, "leaver_status": 0, "last_hits": 36, "denies": 0, "gold_per_min": 321, "xp_per_min": 384, "level": 11, "hero_name": "Axe", "item_0_name": "Blink Dagger", "item_1_name": "Stout Shield", "item_2_name": "Ring of Protection", "item_3_name": "Tranquil Boots", "item_4_name": "Robe of the Magi", "item_5_name": "Town Portal Scroll", "leaver_status_name": "NONE", "leaver_status_description": "finished match, no abandon"}, {"account_id": 4294967295, "player_slot": 2, "hero_id": 10, "item_0": 212, "item_1": 34, "item_2": 69, "item_3": 0, "item_4": 63, "item_5": 46, "backpack_0": 0, "backpack_1": 0, "backpack_2": 0, "kills": 3, "deaths": 2, "assists": 8, "leaver_status": 0, "last_hits": 62, "denies": 7, "gold_per_min": 339, "xp_per_min": 454, "level": 12, "hero_name": "Morphling", "item_0_name": "Ring of Aquila", "item_1_name": "Magic Stick", "item_2_name": "Perseverance", "item_4_name": "Power Treads", "item_5_name": "Town Portal Scroll", "leaver_status_name": "NONE", "leaver_status_description": "finished match, no abandon"}, {"account_id": 4294967295, "player_slot": 3, "hero_id": 14, "item_0": 214, "item_1": 40, "item_2": 41, "item_3": 46, "item_4": 232, "item_5": 0, "backpack_0": 0, "backpack_1": 0, "backpack_2": 0, "kills": 10, "deaths": 3, "assists": 9, "leaver_status": 0, "last_hits": 8, "denies": 1, "gold_per_min": 309, "xp_per_min": 248, "level": 8, "hero_name": "Pudge", "item_0_name": "Tranquil Boots", "item_1_name": "Dust of Appearance", "item_2_name": "Bottle", "item_3_name": "Town Portal Scroll", "item_4_name": "Aether Lens", "leaver_status_name": "NONE", "leaver_status_description": "finished match, no abandon"}, {"account_id": 855286643, "player_slot": 4, "hero_id": 31, "item_0": 214, "item_1": 27, "item_2": 36, "item_3": 0, "item_4": 23, "item_5": 0, "backpack_0": 0, "backpack_1": 0, "backpack_2": 0, "kills": 4, "deaths": 2, "assists": 8, "leaver_status": 0, "last_hits": 13, "denies": 2, "gold_per_min": 260, "xp_per_min": 340, "level": 10, "hero_name": "Lich", "item_0_name": "Tranquil Boots", "item_1_name": "Ring of Regen", "item_2_name": "Magic Wand", "item_4_name": "Staff of Wizardry", "leaver_status_name": "NONE", "leaver_status_description": "finished match, no abandon"}, {"account_id": 4294967295, "player_slot": 128, "hero_id": 49, "item_0": 0, "item_1": 0, "item_2": 0, "item_3": 0, "item_4": 0, "item_5": 0, "backpack_0": 0, "backpack_1": 0, "backpack_2": 0, "kills": 0, "deaths": 2, "assists": 0, "leaver_status": 2, "last_hits": 1, "denies": 0, "gold_per_min": 132, "xp_per_min": 29, "level": 2, "hero_name": "Dragon Knight", "leaver_status_name": "DISCONNECTED_TOO_LONG", "leaver_status_description": "player DC > 5min, abandon"}, {"account_id": 4294967295, "player_slot": 129, "hero_id": 12, "item_0": 212, "item_1": 11, "item_2": 63, "item_3": 170, "item_4": 182, "item_5": 0, "backpack_0": 0, "backpack_1": 0, "backpack_2": 0, "kills": 2, "deaths": 6, "assists": 2, "leaver_status": 1, "last_hits": 42, "denies": 4, "gold_per_min": 398, "xp_per_min": 337, "level": 10, "hero_name": "Phantom Lancer", "item_0_name": "Ring of Aquila", "item_1_name": "Quelling Blade", "item_2_name": "Power Treads", "item_3_name": "Yasha", "item_4_name": "Stout Shield", "leaver_status_name": "DISCONNECTED", "leaver_status_description": "player DC, no abandon"}, {"account_id": 437216580, "player_slot": 130, "hero_id": 35, "item_0": 44, "item_1": 212, "item_2": 34, "item_3": 0, "item_4": 0, "item_5": 0, "backpack_0": 0, "backpack_1": 0, "backpack_2": 0, "kills": 0, "deaths": 6, "assists": 0, "leaver_status": 1, "last_hits": 11, "denies": 1, "gold_per_min": 177, "xp_per_min": 85, "level": 4, "hero_name": "Sniper", "item_0_name": "Tango", "item_1_name": "Ring of Aquila", "item_2_name": "Magic Stick", "leaver_status_name": "DISCONNECTED", "leaver_status_description": "player DC, no abandon"}, {"account_id": 118019811, "player_slot": 131, "hero_id": 6, "item_0": 63, "item_1": 212, "item_2": 263, "item_3": 0, "item_4": 0, "item_5": 0, "backpack_0": 0, "backpack_1": 0, "backpack_2": 0, "kills": 7, "deaths": 5, "assists": 2, "leaver_status": 1, "last_hits": 62, "denies": 7, "gold_per_min": 644, "xp_per_min": 595, "level": 14, "hero_name": "Drow Ranger", "item_0_name": "Power Treads", "item_1_name": "Ring of Aquila", "item_2_name": "Hurricane Pike", "leaver_status_name": "DISCONNECTED", "leaver_status_description": "player DC, no abandon"}, {"account_id": 64989974, "player_slot": 132, "hero_id": 5, "item_0": 214, "item_1": 0, "item_2": 218, "item_3": 254, "item_4": 0, "item_5": 0, "backpack_0": 0, "backpack_1": 0, "backpack_2": 0, "kills": 0, "deaths": 8, "assists": 5, "leaver_status": 1, "last_hits": 7, "denies": 5, "gold_per_min": 248, "xp_per_min": 194, "level": 7, "hero_name": "Crystal Maiden", "item_0_name": "Tranquil Boots", "item_2_name": "Observer and Sentry Wards", "item_3_name": "Glimmer Cape", "leaver_status_name": "DISCONNECTED", "leaver_status_description": "player DC, no abandon"}], "radiant_win": true, "duration": 1004, "pre_game_duration": 90, "start_time": 1530909204, "match_id": 3992212241, "match_seq_num": 3463765623, "tower_status_radiant": 2046, "tower_status_dire": 1974, "barracks_status_radiant": 63, "barracks_status_dire": 63, "cluster": 131, "first_blood_time": 57, "lobby_type": 0, "human_players": 10, "leagueid": 0, "positive_votes": 0, "negative_votes": 0, "game_mode": 22, "flags": 1, "engine": 1, "radiant_score": 27, "dire_score": 10, "picks_bans": [{"is_pick": false, "hero_id": 32, "team": 0, "order": 0}, {"is_pick": false, "hero_id": 94, "team": 0, "order": 1}, {"is_pick": false, "hero_id": 99, "team": 0, "order": 2}], "lobby_name": "Public matchmaking", "game_mode_name": "Ranked All Pick", "cluster_name": "Europe West"}