{"players": [{"account_id": 4294967295, "player_slot": 0, "hero_id": 95, "item_0": 81, "item_1": 154, "item_2": 50, "item_3": 156, "item_4": 139, "item_5": 135, "backpack_0": 11, "backpack_1": 0, "backpack_2": 0, "kills": 11, "deaths": 9, "assists": 10, "leaver_status": 0, "last_hits": 42, "denies": 6, "gold_per_min": 836, "xp_per_min": 1513, "level": 25, "hero_damage": 32221, "tower_damage": 2350, "hero_healing": 2928, "gold": 1923, "gold_spent": 26075, "scaled_hero_damage": 13970, "scaled_tower_damage": 1568, "scaled_hero_healing": 1062, "ability_upgrades": [{"ability": 5508, "time": 116, "level": 1}, {"ability": 5509, "time": 247, "level": 2}, {"ability": 5510, "time": 299, "level": 3}, {"ability": 5511, "time": 346, "level": 4}, {"ability": 5509, "time": 379, "level": 5}, {"ability": 5512, "time": 429, "level": 6}, {"ability": 5511, "time": 474, "level": 7}, {"ability": 5903, "time": 481, "level": 8}, {"ability": 5511, "time": 485, "level": 9}, {"ability": 5511, "time": 487, "level": 10}, {"ability": 5510, "time": 494, "level": 11}, {"ability": 5512, "time": 601, "level": 12}, {"ability": 5508, "time": 674, "level": 13}, {"ability": 5508, "time": 742, "level": 14}, {"ability": 5508, "time": 841, "level": 15}, {"ability": 6959, "time": 885, "level": 16}, {"ability": 5512, "time": 899, "level": 17}, {"ability": 5973, "time": 1004, "level": 18}, {"ability": 6154, "time": 1342, "level": 19}], "hero_name": "Troll Warlord", "item_0_name": "Vladmir's Offering", "item_1_name": "Sange and Yasha", "item_2_name": "Phase Boots", "item_3_name": "Satanic", "item_4_name": "Butterfly", "item_5_name": "Monkey King Bar", "leaver_status_name": "NONE", "leaver_status_description": "finished match, no abandon"}, {"account_id": 4294967295, "player_slot": 1, "hero_id": 75, "item_0": 263, "item_1": 206, "item_2": 96, "item_3": 250, "item_4": 214, "item_5": 133, "backpack_0": 0, "backpack_1": 0, "backpack_2": 77, "kills": 13, "deaths": 7, "assists": 14, "leaver_status": 0, "last_hits": 88, "denies": 8, "gold_per_min": 1115, "xp_per_min": 1580, "level": 25, "hero_damage": 33055, "tower_damage": 1046, "hero_healing": 0, "gold": 12086, "gold_spent": 23040, "scaled_hero_damage": 16915, "scaled_tower_damage": 578, "scaled_hero_healing": 0, "ability_upgrades": [{"ability": 5377, "time": 112, "level": 1}, {"ability": 5379, "time": 219, "level": 2}, {"ability": 5378, "time": 259, "level": 3}, {"ability": 5378, "time": 335, "level": 4}, {"ability": 5378, "time": 384, "level": 5}, {"ability": 5380, "time": 513, "level": 6}, {"ability": 5378, "time": 531, "level": 7}, {"ability": 5377, "time": 563, "level": 8}, {"ability": 5377, "time": 614, "level": 9}, {"ability": 6016, "time": 674, "level": 10}, {"ability": 5377, "time": 688, "level": 11}, {"ability": 5380, "time": 780, "level": 12}, {"ability": 5379, "time": 832, "level": 13}, {"ability": 5379, "time": 833, "level": 14}, {"ability": 6878, "time": 867, "level": 15}, {"ability": 5379, "time": 902, "level": 16}, {"ability": 5380, "time": 940, "level": 17}, {"ability": 5944, "time": 1005, "level": 18}, {"ability": 6879, "time": 1224, "level": 19}], "hero_name": "Silencer", "item_0_name": "Hurricane Pike", "item_1_name": "Rod of Atos", "item_2_name": "Scythe of Vyse", "item_3_name": "Bloodthorn", "item_4_name": "Tranquil Boots", "item_5_name": "Divine Rapier", "leaver_status_name": "NONE", "leaver_status_description": "finished match, no abandon"}, {"account_id": 4294967295, "player_slot": 2, "hero_id": 41, "item_0": 147, "item_1": 141, "item_2": 50, "item_3": 141, "item_4": 43, "item_5": 166, "backpack_0": 0, "backpack_1": 0, "backpack_2": 0, "kills": 7, "deaths": 7, "assists": 16, "leaver_status": 0, "last_hits": 74, "denies": 4, "gold_per_min": 969, "xp_per_min": 1381, "level": 25, "hero_damage": 37528, "tower_damage": 3072, "hero_healing": 0, "gold": 9946, "gold_spent": 20925, "scaled_hero_damage": 14011, "scaled_tower_damage": 1506, "scaled_hero_healing": 0, "ability_upgrades": [{"ability": 5182, "time": 109, "level": 1}, {"ability": 5184, "time": 233, "level": 2}, {"ability": 5184, "time": 251, "level": 3}, {"ability": 5182, "time": 278, "level": 4}, {"ability": 5182, "time": 326, "level": 5}, {"ability": 5185, "time": 384, "level": 6}, {"ability": 5691, "time": 491, "level": 7}, {"ability": 5691, "time": 522, "level": 8}, {"ability": 5182, "time": 553, "level": 9}, {"ability": 5938, "time": 625, "level": 10}, {"ability": 5184, "time": 712, "level": 11}, {"ability": 5184, "time": 784, "level": 12}, {"ability": 5185, "time": 866, "level": 13}, {"ability": 5691, "time": 880, "level": 14}, {"ability": 6807, "time": 891, "level": 15}, {"ability": 5185, "time": 952, "level": 16}, {"ability": 5691, "time": 961, "level": 17}, {"ability": 6210, "time": 970, "level": 18}, {"ability": 6651, "time": 1444, "level": 19}], "hero_name": "Faceless Void", "item_0_name": "Manta Style", "item_1_name": "Daedalus", "item_2_name": "Phase Boots", "item_3_name": "Daedalus", "item_4_name": "Sentry Ward", "item_5_name": "Maelstrom", "leaver_status_name": "NONE", "leaver_status_description": "finished match, no abandon"}, {"account_id": 4294967295, "player_slot": 3, "hero_id": 91, "item_0": 231, "item_1": 36, "item_2": 152, "item_3": 114, "item_4": 40, "item_5": 0, "backpack_0": 0, "backpack_1": 43, "backpack_2": 0, "kills": 0, "deaths": 6, "assists": 13, "leaver_status": 0, "last_hits": 18, "denies": 5, "gold_per_min": 535, "xp_per_min": 1019, "level": 25, "hero_damage": 6305, "tower_damage": 100, "hero_healing": 13587, "gold": 698, "gold_spent": 16470, "scaled_hero_damage": 2563, "scaled_tower_damage": 50, "scaled_hero_healing": 4438, "ability_upgrades": [{"ability": 5485, "time": 132, "level": 1}, {"ability": 5486, "time": 230, "level": 2}, {"ability": 5486, "time": 273, "level": 3}, {"ability": 5485, "time": 315, "level": 4}, {"ability": 5487, "time": 391, "level": 5}, {"ability": 5488, "time": 478, "level": 6}, {"ability": 5485, "time": 576, "level": 7}, {"ability": 5485, "time": 577, "level": 8}, {"ability": 5486, "time": 717, "level": 9}, {"ability": 6253, "time": 817, "level": 10}, {"ability": 5486, "time": 819, "level": 11}, {"ability": 5488, "time": 864, "level": 12}, {"ability": 5487, "time": 872, "level": 13}, {"ability": 5487, "time": 916, "level": 14}, {"ability": 6924, "time": 947, "level": 15}, {"ability": 5487, "time": 977, "level": 16}, {"ability": 5488, "time": 1021, "level": 17}, {"ability": 7188, "time": 1175, "level": 18}, {"ability": 7070, "time": 1928, "level": 19}], "hero_name": "Io", "item_0_name": "Guardian Greaves", "item_1_name": "Magic Wand", "item_2_name": "Shadow Blade", "item_3_name": "Heart of Tarrasque", "item_4_name": "Dust of Appearance", "leaver_status_name": "NONE", "leaver_status_description": "finished match, no abandon"}, {"account_id": 4294967295, "player_slot": 4, "hero_id": 15, "item_0": 114, "item_1": 0, "item_2": 116, "item_3": 48, "item_4": 154, "item_5": 263, "backpack_0": 0, "backpack_1": 0, "backpack_2": 0, "kills": 12, "deaths": 8, "assists": 15, "leaver_status": 0, "last_hits": 115, "denies": 0, "gold_per_min": 1006, "xp_per_min": 1676, "level": 25, "hero_damage": 52502, "tower_damage": 3804, "hero_healing": 0, "gold": 604, "gold_spent": 30480, "scaled_hero_damage": 25119, "scaled_tower_damage": 2198, "scaled_hero_healing": 0, "ability_upgrades": [{"ability": 5083, "time": 115, "level": 1}, {"ability": 5082, "time": 230, "level": 2}, {"ability": 5083, "time": 273, "level": 3}, {"ability": 5082, "time": 370, "level": 4}, {"ability": 5083, "time": 442, "level": 5}, {"ability": 5085, "time": 493, "level": 6}, {"ability": 5083, "time": 536, "level": 7}, {"ability": 5084, "time": 547, "level": 8}, {"ability": 5084, "time": 574, "level": 9}, {"ability": 5085, "time": 618, "level": 10}, {"ability": 5929, "time": 634, "level": 11}, {"ability": 5082, "time": 637, "level": 12}, {"ability": 5082, "time": 657, "level": 13}, {"ability": 5084, "time": 733, "level": 14}, {"ability": 5084, "time": 735, "level": 15}, {"ability": 5085, "time": 816, "level": 16}, {"ability": 6028, "time": 848, "level": 17}, {"ability": 6408, "time": 858, "level": 18}, {"ability": 6037, "time": 1202, "level": 19}], "hero_name": "Razor", "item_0_name": "Heart of Tarrasque", "item_2_name": "Black King Bar", "item_3_name": "Boots of Travel", "item_4_name": "Sange and Yasha", "item_5_name": "Hurricane Pike", "leaver_status_name": "NONE", "leaver_status_description": "finished match, no abandon"}, {"account_id": 4294967295, "player_slot": 128, "hero_id": 70, "item_0": 249, "item_1": 208, "item_2": 127, "item_3": 135, "item_4": 156, "item_5": 48, "backpack_0": 1, "backpack_1": 0, "backpack_2": 0, "kills": 23, "deaths": 8, "assists": 9, "leaver_status": 0, "last_hits": 57, "denies": 6, "gold_per_min": 1160, "xp_per_min": 1592, "level": 25, "hero_damage": 71368, "tower_damage": 1927, "hero_healing": 0, "gold": 936, "gold_spent": 30785, "scaled_hero_damage": 33562, "scaled_tower_damage": 952, "scaled_hero_healing": 0, "ability_upgrades": [{"ability": 5359, "time": 114, "level": 1}, {"ability": 5357, "time": 207, "level": 2}, {"ability": 5359, "time": 232, "level": 3}, {"ability": 5358, "time": 271, "level": 4}, {"ability": 5359, "time": 329, "level": 5}, {"ability": 5360, "time": 333, "level": 6}, {"ability": 5358, "time": 354, "level": 7}, {"ability": 5359, "time": 400, "level": 8}, {"ability": 6160, "time": 446, "level": 9}, {"ability": 5358, "time": 448, "level": 10}, {"ability": 5358, "time": 517, "level": 11}, {"ability": 5360, "time": 623, "level": 12}, {"ability": 5357, "time": 624, "level": 13}, {"ability": 6170, "time": 753, "level": 14}, {"ability": 5357, "time": 754, "level": 15}, {"ability": 5357, "time": 804, "level": 16}, {"ability": 5360, "time": 914, "level": 17}, {"ability": 6974, "time": 977, "level": 18}, {"ability": 7133, "time": 1233, "level": 19}], "hero_name": "Ursa", "item_0_name": "Silver Edge", "item_1_name": "Abyssal Blade", "item_2_name": "Blade Mail", "item_3_name": "Monkey King Bar", "item_4_name": "Satanic", "item_5_name": "Boots of Travel", "leaver_status_name": "NONE", "leaver_status_description": "finished match, no abandon"}, {"account_id": 84895526, "player_slot": 129, "hero_id": 19, "item_0": 41, "item_1": 141, "item_2": 249, "item_3": 50, "item_4": 252, "item_5": 112, "backpack_0": 44, "backpack_1": 36, "backpack_2": 0, "kills": 8, "deaths": 8, "assists": 9, "leaver_status": 0, "last_hits": 77, "denies": 0, "gold_per_min": 859, "xp_per_min": 1524, "level": 25, "hero_damage": 24022, "tower_damage": 7627, "hero_healing": 0, "gold": 514, "gold_spent": 22670, "scaled_hero_damage": 11988, "scaled_tower_damage": 4603, "scaled_hero_healing": 0, "ability_upgrades": [{"ability": 5108, "time": 109, "level": 1}, {"ability": 5106, "time": 255, "level": 2}, {"ability": 5107, "time": 324, "level": 3}, {"ability": 5108, "time": 344, "level": 4}, {"ability": 5107, "time": 379, "level": 5}, {"ability": 6937, "time": 464, "level": 6}, {"ability": 5107, "time": 555, "level": 7}, {"ability": 5109, "time": 603, "level": 8}, {"ability": 5107, "time": 694, "level": 9}, {"ability": 5108, "time": 774, "level": 10}, {"ability": 5939, "time": 802, "level": 11}, {"ability": 5106, "time": 816, "level": 12}, {"ability": 5109, "time": 886, "level": 13}, {"ability": 5106, "time": 905, "level": 14}, {"ability": 5106, "time": 950, "level": 15}, {"ability": 6153, "time": 985, "level": 16}, {"ability": 5109, "time": 1013, "level": 17}, {"ability": 6934, "time": 1043, "level": 18}, {"ability": 6932, "time": 1357, "level": 19}], "hero_name": "Tiny", "item_0_name": "Bottle", "item_1_name": "Daedalus", "item_2_name": "Silver Edge", "item_3_name": "Phase Boots", "item_4_name": "Echo Sabre", "item_5_name": "Assault Cuirass", "leaver_status_name": "NONE", "leaver_status_description": "finished match, no abandon"}, {"account_id": 64989974, "player_slot": 130, "hero_id": 66, "item_0": 102, "item_1": 187, "item_2": 254, "item_3": 185, "item_4": 90, "item_5": 81, "backpack_0": 0, "backpack_1": 0, "backpack_2": 0, "kills": 0, "deaths": 9, "assists": 23, "leaver_status": 0, "last_hits": 6, "denies": 5, "gold_per_min": 585, "xp_per_min": 1197, "level": 25, "hero_damage": 3831, "tower_damage": 670, "hero_healing": 5057, "gold": 1454, "gold_spent": 15175, "scaled_hero_damage": 2625, "scaled_tower_damage": 390, "scaled_hero_healing": 1325, "ability_upgrades": [{"ability": 5328, "time": 107, "level": 1}, {"ability": 5330, "time": 256, "level": 2}, {"ability": 5330, "time": 351, "level": 3}, {"ability": 7306, "time": 400, "level": 4}, {"ability": 5330, "time": 461, "level": 5}, {"ability": 5331, "time": 492, "level": 6}, {"ability": 5328, "time": 592, "level": 7}, {"ability": 5330, "time": 657, "level": 8}, {"ability": 5328, "time": 735, "level": 9}, {"ability": 6114, "time": 743, "level": 10}, {"ability": 5328, "time": 745, "level": 11}, {"ability": 5331, "time": 858, "level": 12}, {"ability": 7306, "time": 877, "level": 13}, {"ability": 7306, "time": 907, "level": 14}, {"ability": 6363, "time": 947, "level": 15}, {"ability": 7306, "time": 950, "level": 16}, {"ability": 5331, "time": 1032, "level": 17}, {"ability": 6026, "time": 1103, "level": 18}, {"ability": 6260, "time": 1597, "level": 19}], "hero_name": "Chen", "item_0_name": "Force Staff", "item_1_name": "Medallion of Courage", "item_2_name": "Glimmer Cape", "item_3_name": "Drum of Endurance", "item_4_name": "Pipe of Insight", "item_5_name": "Vladmir's Offering", "leaver_status_name": "NONE", "leaver_status_description": "finished match, no abandon"}, {"account_id": 437216580, "player_slot": 131, "hero_id": 114, "item_0": 168, "item_1": 0, "item_2": 152, "item_3": 252, "item_4": 201, "item_5": 214, "backpack_0": 0, "backpack_1": 0, "backpack_2": 0, "kills": 0, "deaths": 10, "assists": 13, "leaver_status": 0, "last_hits": 13, "denies": 0, "gold_per_min": 476, "xp_per_min": 1565, "level": 25, "hero_damage": 16344, "tower_damage": 19, "hero_healing": 0, "gold": 828, "gold_spent": 14640, "scaled_hero_damage": 7220, "scaled_tower_damage": 7, "scaled_hero_healing": 0, "ability_upgrades": [{"ability": 5723, "time": 108, "level": 1}, {"ability": 5716, "time": 213, "level": 2}, {"ability": 5721, "time": 270, "level": 3}, {"ability": 5723, "time": 388, "level": 4}, {"ability": 5721, "time": 454, "level": 5}, {"ability": 5725, "time": 573, "level": 6}, {"ability": 5723, "time": 585, "level": 7}, {"ability": 5723, "time": 662, "level": 8}, {"ability": 5716, "time": 737, "level": 9}, {"ability": 5906, "time": 821, "level": 10}, {"ability": 5716, "time": 860, "level": 11}, {"ability": 5725, "time": 975, "level": 12}, {"ability": 5716, "time": 982, "level": 13}, {"ability": 7038, "time": 985, "level": 14}, {"ability": 5721, "time": 986, "level": 15}, {"ability": 5721, "time": 994, "level": 16}, {"ability": 5725, "time": 1018, "level": 17}, {"ability": 6303, "time": 1099, "level": 18}, {"ability": 7025, "time": 1262, "level": 19}], "hero_name": "Monkey King", "item_0_name": "Desolator", "item_2_name": "Shadow Blade", "item_3_name": "Echo Sabre", "item_4_name": "Dagon", "item_5_name": "Tranquil Boots", "leaver_status_name": "NONE", "leaver_status_description": "finished match, no abandon"}, {"account_id": 4294967295, "player_slot": 132, "hero_id": 23, "item_0": 152, "item_1": 116, "item_2": 50, "item_3": 141, "item_4": 149, "item_5": 247, "backpack_0": 41, "backpack_1": 218, "backpack_2": 0, "kills": 6, "deaths": 8, "assists": 13, "leaver_status": 0, "last_hits": 75, "denies": 0, "gold_per_min": 793, "xp_per_min": 1676, "level": 25, "hero_damage": 27453, "tower_damage": 1847, "hero_healing": 0, "gold": 1565, "gold_spent": 22875, "scaled_hero_damage": 13271, "scaled_tower_damage": 1001, "scaled_hero_healing": 0, "ability_upgrades": [{"ability": 5032, "time": 117, "level": 1}, {"ability": 5031, "time": 213, "level": 2}, {"ability": 5033, "time": 274, "level": 3}, {"ability": 5032, "time": 329, "level": 4}, {"ability": 5032, "time": 410, "level": 5}, {"ability": 5035, "time": 456, "level": 6}, {"ability": 5032, "time": 560, "level": 7}, {"ability": 5031, "time": 606, "level": 8}, {"ability": 5031, "time": 644, "level": 9}, {"ability": 5940, "time": 746, "level": 10}, {"ability": 5031, "time": 768, "level": 11}, {"ability": 5035, "time": 816, "level": 12}, {"ability": 5033, "time": 818, "level": 13}, {"ability": 5033, "time": 880, "level": 14}, {"ability": 5033, "time": 890, "level": 15}, {"ability": 6385, "time": 910, "level": 16}, {"ability": 5035, "time": 973, "level": 17}, {"ability": 5984, "time": 987, "level": 18}, {"ability": 7131, "time": 1209, "level": 19}], "hero_name": "Kunkka", "item_0_name": "Shadow Blade", "item_1_name": "Black King Bar", "item_2_name": "Phase Boots", "item_3_name": "Daedalus", "item_4_name": "Crystalys", "item_5_name": "Moon Shard", "leaver_status_name": "NONE", "leaver_status_description": "finished match, no abandon"}], "radiant_win": true, "duration": 1857, "pre_game_duration": 60, "start_time": 1547759011, "match_id": 4341250873, "match_seq_num": 3763068314, "tower_status_radiant": 1280, "tower_status_dire": 260, "barracks_status_radiant": 51, "barracks_status_dire": 51, "cluster": 131, "first_blood_time": 143, "lobby_type": 0, "human_players": 10, "leagueid": 0, "positive_votes": 0, "negative_votes": 0, "game_mode": 23, "flags": 1, "engine": 1, "radiant_score": 43, "dire_score": 37, "picks_bans": [{"is_pick": false, "hero_id": 11, "team": 0, "order": 0}, {"is_pick": false, "hero_id": 74, "team": 0, "order": 1}, {"is_pick": false, "hero_id": 32, "team": 0, "order": 2}, {"is_pick": false, "hero_id": 35, "team": 0, "order": 3}, {"is_pick": false, "hero_id": 105, "team": 0, "order": 4}, {"is_pick": false, "hero_id": 71, "team": 1, "order": 5}, {"is_pick": false, "hero_id": 99, "team": 1, "order": 6}], "lobby_name": "Public matchmaking", "cluster_name": "Europe West"}