{"players": [{"account_id": 158320620, "player_slot": 0, "hero_id": 1, "item_0": 125, "item_1": 145, "item_2": 247, "item_3": 48, "item_4": 170, "item_5": 0, "backpack_0": 0, "backpack_1": 0, "backpack_2": 0, "kills": 1, "deaths": 3, "assists": 4, "leaver_status": 0, "last_hits": 111, "denies": 8, "gold_per_min": 701, "xp_per_min": 973, "level": 23, "hero_damage": 5285, "tower_damage": 913, "hero_healing": 0, "gold": 2750, "gold_spent": 15380, "scaled_hero_damage": 3421, "scaled_tower_damage": 492, "scaled_hero_healing": 0, "ability_upgrades": [{"ability": 5003, "time": 158, "level": 1}, {"ability": 5004, "time": 207, "level": 2}, {"ability": 5003, "time": 265, "level": 3}, {"ability": 5004, "time": 322, "level": 4}, {"ability": 5003, "time": 395, "level": 5}, {"ability": 5006, "time": 466, "level": 6}, {"ability": 5003, "time": 562, "level": 7}, {"ability": 5004, "time": 581, "level": 8}, {"ability": 5004, "time": 600, "level": 9}, {"ability": 6137, "time": 706, "level": 10}, {"ability": 7314, "time": 743, "level": 11}, {"ability": 5006, "time": 798, "level": 12}, {"ability": 7314, "time": 828, "level": 13}, {"ability": 7314, "time": 929, "level": 14}, {"ability": 5929, "time": 1039, "level": 15}, {"ability": 7314, "time": 1072, "level": 16}, {"ability": 5006, "time": 1130, "level": 17}, {"ability": 6012, "time": 1298, "level": 18}], "hero_name": "Anti-Mage", "item_0_name": "Vanguard", "item_1_name": "Battle Fury", "item_2_name": "Moon Shard", "item_3_name": "Boots of Travel", "item_4_name": "Yasha", "leaver_status_name": "NONE", "leaver_status_description": "finished match, no abandon"}, {"account_id": 403773466, "player_slot": 1, "hero_id": 74, "item_0": 244, "item_1": 108, "item_2": 29, "item_3": 123, "item_4": 65, "item_5": 1, "backpack_0": 57, "backpack_1": 23, "backpack_2": 0, "kills": 4, "deaths": 3, "assists": 7, "leaver_status": 0, "last_hits": 56, "denies": 10, "gold_per_min": 704, "xp_per_min": 861, "level": 22, "hero_damage": 16445, "tower_damage": 42, "hero_healing": 0, "gold": 612, "gold_spent": 18090, "scaled_hero_damage": 9695, "scaled_tower_damage": 9, "scaled_hero_healing": 0, "ability_upgrades": [{"ability": 5372, "time": 91, "level": 1}, {"ability": 5370, "time": 191, "level": 2}, {"ability": 5372, "time": 209, "level": 3}, {"ability": 5370, "time": 248, "level": 4}, {"ability": 5372, "time": 276, "level": 5}, {"ability": 5371, "time": 304, "level": 6}, {"ability": 5372, "time": 334, "level": 7}, {"ability": 5370, "time": 384, "level": 8}, {"ability": 5372, "time": 422, "level": 9}, {"ability": 5371, "time": 449, "level": 10}, {"ability": 5372, "time": 523, "level": 11}, {"ability": 5371, "time": 556, "level": 12}, {"ability": 5372, "time": 608, "level": 13}, {"ability": 5371, "time": 736, "level": 14}, {"ability": 5370, "time": 824, "level": 15}, {"ability": 5371, "time": 879, "level": 16}, {"ability": 5371, "time": 970, "level": 17}, {"ability": 5371, "time": 1133, "level": 18}, {"ability": 5370, "time": 1134, "level": 19}, {"ability": 5370, "time": 1289, "level": 20}, {"ability": 5370, "time": 1291, "level": 21}, {"ability": 6811, "time": 1369, "level": 22}], "hero_name": "Invoker", "item_0_name": "Wind Lace", "item_1_name": "Aghanim's Scepter", "item_2_name": "Boots of Speed", "item_3_name": "Linken's Sphere", "item_4_name": "Hand of Midas", "item_5_name": "Blink Dagger", "leaver_status_name": "NONE", "leaver_status_description": "finished match, no abandon"}, {"account_id": 4294967295, "player_slot": 2, "hero_id": 12, "item_0": 29, "item_1": 208, "item_2": 174, "item_3": 149, "item_4": 0, "item_5": 114, "backpack_0": 0, "backpack_1": 0, "backpack_2": 0, "kills": 6, "deaths": 9, "assists": 2, "leaver_status": 0, "last_hits": 68, "denies": 1, "gold_per_min": 765, "xp_per_min": 1336, "level": 25, "hero_damage": 16901, "tower_damage": 358, "hero_healing": 0, "gold": 1240, "gold_spent": 18745, "scaled_hero_damage": 8431, "scaled_tower_damage": 190, "scaled_hero_healing": 0, "ability_upgrades": [{"ability": 5068, "time": 126, "level": 1}, {"ability": 5065, "time": 236, "level": 2}, {"ability": 5066, "time": 302, "level": 3}, {"ability": 5065, "time": 380, "level": 4}, {"ability": 5065, "time": 488, "level": 5}, {"ability": 5067, "time": 507, "level": 6}, {"ability": 5065, "time": 576, "level": 7}, {"ability": 5066, "time": 618, "level": 8}, {"ability": 5066, "time": 641, "level": 9}, {"ability": 5066, "time": 719, "level": 10}, {"ability": 5906, "time": 795, "level": 11}, {"ability": 5067, "time": 825, "level": 12}, {"ability": 5068, "time": 827, "level": 13}, {"ability": 5068, "time": 960, "level": 14}, {"ability": 6400, "time": 988, "level": 15}, {"ability": 5068, "time": 1082, "level": 16}, {"ability": 5067, "time": 1153, "level": 17}, {"ability": 6849, "time": 1306, "level": 18}, {"ability": 6851, "time": 1428, "level": 19}], "hero_name": "Phantom Lancer", "item_0_name": "Boots of Speed", "item_1_name": "Abyssal Blade", "item_2_name": "Diffusal Blade", "item_3_name": "Crystalys", "item_5_name": "Heart of Tarrasque", "leaver_status_name": "NONE", "leaver_status_description": "finished match, no abandon"}, {"account_id": 4294967295, "player_slot": 3, "hero_id": 63, "item_0": 168, "item_1": 75, "item_2": 123, "item_3": 29, "item_4": 236, "item_5": 55, "backpack_0": 0, "backpack_1": 0, "backpack_2": 0, "kills": 4, "deaths": 8, "assists": 4, "leaver_status": 0, "last_hits": 31, "denies": 4, "gold_per_min": 624, "xp_per_min": 1019, "level": 24, "hero_damage": 19075, "tower_damage": 608, "hero_healing": 0, "gold": 2046, "gold_spent": 14195, "scaled_hero_damage": 9145, "scaled_tower_damage": 524, "scaled_hero_healing": 0, "ability_upgrades": [{"ability": 5290, "time": 139, "level": 1}, {"ability": 5291, "time": 236, "level": 2}, {"ability": 5290, "time": 271, "level": 3}, {"ability": 5291, "time": 300, "level": 4}, {"ability": 5290, "time": 378, "level": 5}, {"ability": 5292, "time": 468, "level": 6}, {"ability": 5291, "time": 519, "level": 7}, {"ability": 5289, "time": 590, "level": 8}, {"ability": 5290, "time": 621, "level": 9}, {"ability": 5289, "time": 737, "level": 10}, {"ability": 6372, "time": 841, "level": 11}, {"ability": 5292, "time": 867, "level": 12}, {"ability": 5291, "time": 890, "level": 13}, {"ability": 6987, "time": 958, "level": 14}, {"ability": 5289, "time": 960, "level": 15}, {"ability": 5289, "time": 983, "level": 16}, {"ability": 5292, "time": 1124, "level": 17}, {"ability": 6988, "time": 1224, "level": 18}], "hero_name": "Weaver", "item_0_name": "Desolator", "item_1_name": "Wraith Band", "item_2_name": "Linken's Sphere", "item_3_name": "Boots of Speed", "item_4_name": "Dragon Lance", "item_5_name": "Hyperstone", "leaver_status_name": "NONE", "leaver_status_description": "finished match, no abandon"}, {"account_id": 121108078, "player_slot": 4, "hero_id": 76, "item_0": 63, "item_1": 123, "item_2": 102, "item_3": 218, "item_4": 259, "item_5": 0, "backpack_0": 0, "backpack_1": 0, "backpack_2": 0, "kills": 2, "deaths": 7, "assists": 5, "leaver_status": 0, "last_hits": 23, "denies": 0, "gold_per_min": 533, "xp_per_min": 1138, "level": 25, "hero_damage": 10964, "tower_damage": 78, "hero_healing": 0, "gold": 1712, "gold_spent": 12450, "scaled_hero_damage": 6626, "scaled_tower_damage": 37, "scaled_hero_healing": 0, "ability_upgrades": [{"ability": 5392, "time": 92, "level": 1}, {"ability": 5684, "time": 208, "level": 2}, {"ability": 5392, "time": 263, "level": 3}, {"ability": 5391, "time": 318, "level": 4}, {"ability": 5392, "time": 394, "level": 5}, {"ability": 5394, "time": 470, "level": 6}, {"ability": 5392, "time": 552, "level": 7}, {"ability": 5391, "time": 576, "level": 8}, {"ability": 5684, "time": 671, "level": 9}, {"ability": 5391, "time": 753, "level": 10}, {"ability": 5684, "time": 889, "level": 11}, {"ability": 5394, "time": 1078, "level": 12}, {"ability": 5391, "time": 1133, "level": 13}, {"ability": 5684, "time": 1133, "level": 14}, {"ability": 5903, "time": 1136, "level": 15}, {"ability": 5394, "time": 1290, "level": 16}, {"ability": 6141, "time": 1302, "level": 17}, {"ability": 6080, "time": 1341, "level": 18}], "hero_name": "Outworld Devourer", "item_0_name": "Power Treads", "item_1_name": "Linken's Sphere", "item_2_name": "Force Staff", "item_3_name": "Observer and Sentry Wards", "leaver_status_name": "NONE", "leaver_status_description": "finished match, no abandon"}, {"account_id": 4294967295, "player_slot": 128, "hero_id": 52, "item_0": 77, "item_1": 152, "item_2": 100, "item_3": 36, "item_4": 121, "item_5": 277, "backpack_0": 0, "backpack_1": 77, "backpack_2": 0, "kills": 5, "deaths": 4, "assists": 9, "leaver_status": 0, "last_hits": 41, "denies": 0, "gold_per_min": 686, "xp_per_min": 885, "level": 22, "hero_damage": 17013, "tower_damage": 2282, "hero_healing": 0, "gold": 1098, "gold_spent": 16665, "scaled_hero_damage": 12504, "scaled_tower_damage": 1436, "scaled_hero_healing": 0, "ability_upgrades": [{"ability": 5243, "time": 98, "level": 1}, {"ability": 5242, "time": 219, "level": 2}, {"ability": 5241, "time": 269, "level": 3}, {"ability": 5243, "time": 341, "level": 4}, {"ability": 5243, "time": 367, "level": 5}, {"ability": 5244, "time": 438, "level": 6}, {"ability": 5243, "time": 541, "level": 7}, {"ability": 5242, "time": 581, "level": 8}, {"ability": 5242, "time": 615, "level": 9}, {"ability": 5932, "time": 677, "level": 10}, {"ability": 5242, "time": 698, "level": 11}, {"ability": 5244, "time": 766, "level": 12}, {"ability": 5241, "time": 912, "level": 13}, {"ability": 5241, "time": 983, "level": 14}, {"ability": 6141, "time": 1052, "level": 15}, {"ability": 5241, "time": 1086, "level": 16}, {"ability": 5244, "time": 1430, "level": 17}, {"ability": 6672, "time": 1533, "level": 18}], "hero_name": "Leshrac", "item_0_name": "Null Talisman", "item_1_name": "Shadow Blade", "item_2_name": "Eul's Scepter of Divinity", "item_3_name": "Magic Wand", "item_4_name": "Bloodstone", "leaver_status_name": "NONE", "leaver_status_description": "finished match, no abandon"}, {"account_id": 385247358, "player_slot": 129, "hero_id": 18, "item_0": 156, "item_1": 1, "item_2": 116, "item_3": 141, "item_4": 50, "item_5": 247, "backpack_0": 0, "backpack_1": 0, "backpack_2": 0, "kills": 10, "deaths": 3, "assists": 8, "leaver_status": 0, "last_hits": 107, "denies": 6, "gold_per_min": 1108, "xp_per_min": 1331, "level": 25, "hero_damage": 27053, "tower_damage": 1810, "hero_healing": 0, "gold": 3748, "gold_spent": 26100, "scaled_hero_damage": 17121, "scaled_tower_damage": 1296, "scaled_hero_healing": 0, "ability_upgrades": [{"ability": 5094, "time": 127, "level": 1}, {"ability": 5096, "time": 219, "level": 2}, {"ability": 5094, "time": 274, "level": 3}, {"ability": 5096, "time": 280, "level": 4}, {"ability": 5096, "time": 343, "level": 5}, {"ability": 5097, "time": 401, "level": 6}, {"ability": 5094, "time": 441, "level": 7}, {"ability": 5096, "time": 516, "level": 8}, {"ability": 5094, "time": 519, "level": 9}, {"ability": 5982, "time": 577, "level": 10}, {"ability": 5095, "time": 665, "level": 11}, {"ability": 5097, "time": 672, "level": 12}, {"ability": 5095, "time": 727, "level": 13}, {"ability": 5095, "time": 775, "level": 14}, {"ability": 6141, "time": 874, "level": 15}, {"ability": 5095, "time": 877, "level": 16}, {"ability": 5097, "time": 973, "level": 17}, {"ability": 6111, "time": 1030, "level": 18}, {"ability": 6910, "time": 1401, "level": 19}], "hero_name": "Sven", "item_0_name": "Satanic", "item_1_name": "Blink Dagger", "item_2_name": "Black King Bar", "item_3_name": "Daedalus", "item_4_name": "Phase Boots", "item_5_name": "Moon Shard", "leaver_status_name": "NONE", "leaver_status_description": "finished match, no abandon"}, {"account_id": 64989974, "player_slot": 130, "hero_id": 36, "item_0": 77, "item_1": 63, "item_2": 204, "item_3": 108, "item_4": 0, "item_5": 40, "backpack_0": 0, "backpack_1": 0, "backpack_2": 0, "kills": 3, "deaths": 4, "assists": 2, "leaver_status": 0, "last_hits": 42, "denies": 8, "gold_per_min": 636, "xp_per_min": 1168, "level": 25, "hero_damage": 10936, "tower_damage": 2713, "hero_healing": 395, "gold": 2092, "gold_spent": 14435, "scaled_hero_damage": 6617, "scaled_tower_damage": 1515, "scaled_hero_healing": 226, "ability_upgrades": [{"ability": 5158, "time": 120, "level": 1}, {"ability": 5159, "time": 215, "level": 2}, {"ability": 5158, "time": 272, "level": 3}, {"ability": 5160, "time": 315, "level": 4}, {"ability": 5158, "time": 409, "level": 5}, {"ability": 5161, "time": 503, "level": 6}, {"ability": 5158, "time": 530, "level": 7}, {"ability": 5159, "time": 611, "level": 8}, {"ability": 5159, "time": 638, "level": 9}, {"ability": 5939, "time": 785, "level": 10}, {"ability": 5159, "time": 834, "level": 11}, {"ability": 5161, "time": 869, "level": 12}, {"ability": 5160, "time": 893, "level": 13}, {"ability": 5160, "time": 988, "level": 14}, {"ability": 7111, "time": 997, "level": 15}, {"ability": 5160, "time": 1072, "level": 16}, {"ability": 5161, "time": 1193, "level": 17}, {"ability": 6444, "time": 1288, "level": 18}, {"ability": 6703, "time": 1590, "level": 19}], "hero_name": "Necrophos", "item_0_name": "Null Talisman", "item_1_name": "Power Treads", "item_2_name": "Dagon", "item_3_name": "Aghanim's Scepter", "item_5_name": "Dust of Appearance", "leaver_status_name": "NONE", "leaver_status_description": "finished match, no abandon"}, {"account_id": 4294967295, "player_slot": 131, "hero_id": 6, "item_0": 263, "item_1": 236, "item_2": 152, "item_3": 116, "item_4": 36, "item_5": 63, "backpack_0": 14, "backpack_1": 20, "backpack_2": 0, "kills": 1, "deaths": 3, "assists": 5, "leaver_status": 0, "last_hits": 74, "denies": 0, "gold_per_min": 683, "xp_per_min": 951, "level": 23, "hero_damage": 6013, "tower_damage": 2872, "hero_healing": 0, "gold": 2011, "gold_spent": 15680, "scaled_hero_damage": 5681, "scaled_tower_damage": 1475, "scaled_hero_healing": 0, "ability_upgrades": [{"ability": 5019, "time": 95, "level": 1}, {"ability": 5021, "time": 217, "level": 2}, {"ability": 5019, "time": 271, "level": 3}, {"ability": 5021, "time": 315, "level": 4}, {"ability": 5019, "time": 410, "level": 5}, {"ability": 5022, "time": 460, "level": 6}, {"ability": 5019, "time": 528, "level": 7}, {"ability": 5021, "time": 641, "level": 8}, {"ability": 5021, "time": 698, "level": 9}, {"ability": 5918, "time": 762, "level": 10}, {"ability": 5632, "time": 828, "level": 11}, {"ability": 5022, "time": 910, "level": 12}, {"ability": 5632, "time": 1062, "level": 13}, {"ability": 5632, "time": 1069, "level": 14}, {"ability": 6016, "time": 1083, "level": 15}, {"ability": 5022, "time": 1173, "level": 16}, {"ability": 5632, "time": 1185, "level": 17}, {"ability": 5974, "time": 1216, "level": 18}], "hero_name": "Drow Ranger", "item_0_name": "Hurricane Pike", "item_1_name": "Dragon Lance", "item_2_name": "Shadow Blade", "item_3_name": "Black King Bar", "item_4_name": "Magic Wand", "item_5_name": "Power Treads", "leaver_status_name": "NONE", "leaver_status_description": "finished match, no abandon"}, {"account_id": 4294967295, "player_slot": 132, "hero_id": 56, "item_0": 98, "item_1": 96, "item_2": 135, "item_3": 216, "item_4": 63, "item_5": 168, "backpack_0": 216, "backpack_1": 44, "backpack_2": 0, "kills": 9, "deaths": 3, "assists": 5, "leaver_status": 0, "last_hits": 112, "denies": 3, "gold_per_min": 953, "xp_per_min": 1652, "level": 25, "hero_damage": 18993, "tower_damage": 1957, "hero_healing": 0, "gold": 4559, "gold_spent": 19890, "scaled_hero_damage": 13342, "scaled_tower_damage": 1012, "scaled_hero_healing": 0, "ability_upgrades": [{"ability": 5260, "time": 92, "level": 1}, {"ability": 5259, "time": 214, "level": 2}, {"ability": 5261, "time": 241, "level": 3}, {"ability": 5260, "time": 315, "level": 4}, {"ability": 5259, "time": 365, "level": 5}, {"ability": 7319, "time": 423, "level": 6}, {"ability": 5260, "time": 482, "level": 7}, {"ability": 5260, "time": 508, "level": 8}, {"ability": 5259, "time": 576, "level": 9}, {"ability": 5932, "time": 579, "level": 10}, {"ability": 5259, "time": 665, "level": 11}, {"ability": 7319, "time": 673, "level": 12}, {"ability": 5261, "time": 765, "level": 13}, {"ability": 5261, "time": 840, "level": 14}, {"ability": 5973, "time": 920, "level": 15}, {"ability": 5261, "time": 988, "level": 16}, {"ability": 7319, "time": 1028, "level": 17}, {"ability": 5944, "time": 1164, "level": 18}, {"ability": 6620, "time": 1290, "level": 19}], "hero_name": "Clinkz", "item_0_name": "Orchid Malevolence", "item_1_name": "Scythe of Vyse", "item_2_name": "Monkey King Bar", "item_3_name": "Enchanted Mango", "item_4_name": "Power Treads", "item_5_name": "Desolator", "leaver_status_name": "NONE", "leaver_status_description": "finished match, no abandon"}], "radiant_win": false, "duration": 1500, "pre_game_duration": 60, "start_time": 1548078071, "match_id": 4350775956, "match_seq_num": 3769880695, "tower_status_radiant": 36, "tower_status_dire": 1972, "barracks_status_radiant": 15, "barracks_status_dire": 63, "cluster": 132, "first_blood_time": 7, "lobby_type": 0, "human_players": 10, "leagueid": 0, "positive_votes": 0, "negative_votes": 0, "game_mode": 23, "flags": 1, "engine": 1, "radiant_score": 17, "dire_score": 30, "picks_bans": [{"is_pick": false, "hero_id": 32, "team": 0, "order": 0}, {"is_pick": false, "hero_id": 26, "team": 0, "order": 1}, {"is_pick": false, "hero_id": 44, "team": 0, "order": 2}, {"is_pick": false, "hero_id": 59, "team": 0, "order": 3}, {"is_pick": false, "hero_id": 41, "team": 0, "order": 4}, {"is_pick": false, "hero_id": 8, "team": 1, "order": 5}, {"is_pick": false, "hero_id": 10, "team": 1, "order": 6}], "lobby_name": "Public matchmaking", "cluster_name": "Europe West"}