{"players": [{"account_id": 4294967295, "player_slot": 0, "hero_id": 10, "item_0": 26, "item_1": 123, "item_2": 61, "item_3": 63, "item_4": 160, "item_5": 53, "backpack_0": 11, "backpack_1": 0, "backpack_2": 0, "kills": 3, "deaths": 7, "assists": 12, "leaver_status": 0, "last_hits": 90, "denies": 1, "gold_per_min": 731, "xp_per_min": 1165, "level": 25, "hero_damage": 11291, "tower_damage": 2745, "hero_healing": 0, "gold": 212, "gold_spent": 17860, "scaled_hero_damage": 5935, "scaled_tower_damage": 1659, "scaled_hero_healing": 0, "ability_upgrades": [{"ability": 5055, "time": 100, "level": 1}, {"ability": 5052, "time": 182, "level": 2}, {"ability": 5055, "time": 211, "level": 3}, {"ability": 5053, "time": 248, "level": 4}, {"ability": 5056, "time": 279, "level": 5}, {"ability": 5057, "time": 327, "level": 6}, {"ability": 5055, "time": 370, "level": 7}, {"ability": 5053, "time": 430, "level": 8}, {"ability": 5052, "time": 448, "level": 9}, {"ability": 6062, "time": 491, "level": 10}, {"ability": 5052, "time": 493, "level": 11}, {"ability": 5057, "time": 625, "level": 12}, {"ability": 5053, "time": 661, "level": 13}, {"ability": 5052, "time": 662, "level": 14}, {"ability": 5907, "time": 754, "level": 15}, {"ability": 7000, "time": 756, "level": 16}, {"ability": 5057, "time": 804, "level": 17}, {"ability": 6840, "time": 926, "level": 18}, {"ability": 7052, "time": 1548, "level": 19}], "hero_name": "Morphling", "item_0_name": "Morbid Mask", "item_1_name": "Linken's Sphere", "item_2_name": "Vitality Booster", "item_3_name": "Power Treads", "item_4_name": "Eye of Skadi", "item_5_name": "Reaver", "leaver_status_name": "NONE", "leaver_status_description": "finished match, no abandon"}, {"account_id": 4294967295, "player_slot": 1, "hero_id": 68, "item_0": 214, "item_1": 77, "item_2": 42, "item_3": 108, "item_4": 0, "item_5": 259, "backpack_0": 0, "backpack_1": 0, "backpack_2": 0, "kills": 2, "deaths": 3, "assists": 15, "leaver_status": 0, "last_hits": 27, "denies": 0, "gold_per_min": 667, "xp_per_min": 1162, "level": 25, "hero_damage": 21722, "tower_damage": 27, "hero_healing": 0, "gold": 5917, "gold_spent": 10765, "scaled_hero_damage": 9378, "scaled_tower_damage": 30, "scaled_hero_healing": 0, "ability_upgrades": [{"ability": 5345, "time": 133, "level": 1}, {"ability": 5347, "time": 240, "level": 2}, {"ability": 5345, "time": 289, "level": 3}, {"ability": 5347, "time": 340, "level": 4}, {"ability": 5345, "time": 469, "level": 5}, {"ability": 5348, "time": 517, "level": 6}, {"ability": 5345, "time": 537, "level": 7}, {"ability": 5347, "time": 579, "level": 8}, {"ability": 5989, "time": 651, "level": 9}, {"ability": 5347, "time": 653, "level": 10}, {"ability": 5346, "time": 726, "level": 11}, {"ability": 5348, "time": 805, "level": 12}, {"ability": 5346, "time": 806, "level": 13}, {"ability": 5346, "time": 807, "level": 14}, {"ability": 6079, "time": 893, "level": 15}, {"ability": 5346, "time": 964, "level": 16}, {"ability": 5348, "time": 1115, "level": 17}, {"ability": 6291, "time": 1292, "level": 18}, {"ability": 7106, "time": 1563, "level": 19}], "hero_name": "Ancient Apparition", "item_0_name": "Tranquil Boots", "item_1_name": "Null Talisman", "item_2_name": "Observer Ward", "item_3_name": "Aghanim's Scepter", "leaver_status_name": "NONE", "leaver_status_description": "finished match, no abandon"}, {"account_id": 64989974, "player_slot": 2, "hero_id": 43, "item_0": 119, "item_1": 50, "item_2": 100, "item_3": 277, "item_4": 77, "item_5": 123, "backpack_0": 0, "backpack_1": 0, "backpack_2": 0, "kills": 7, "deaths": 8, "assists": 10, "leaver_status": 0, "last_hits": 80, "denies": 6, "gold_per_min": 806, "xp_per_min": 1206, "level": 25, "hero_damage": 35656, "tower_damage": 3443, "hero_healing": 0, "gold": 3795, "gold_spent": 19015, "scaled_hero_damage": 12515, "scaled_tower_damage": 1708, "scaled_hero_healing": 0, "ability_upgrades": [{"ability": 5090, "time": 158, "level": 1}, {"ability": 5685, "time": 240, "level": 2}, {"ability": 5090, "time": 280, "level": 3}, {"ability": 5685, "time": 334, "level": 4}, {"ability": 5090, "time": 394, "level": 5}, {"ability": 5093, "time": 473, "level": 6}, {"ability": 5090, "time": 529, "level": 7}, {"ability": 5091, "time": 573, "level": 8}, {"ability": 5685, "time": 605, "level": 9}, {"ability": 5940, "time": 685, "level": 10}, {"ability": 5685, "time": 710, "level": 11}, {"ability": 5093, "time": 760, "level": 12}, {"ability": 5091, "time": 805, "level": 13}, {"ability": 5091, "time": 865, "level": 14}, {"ability": 6056, "time": 871, "level": 15}, {"ability": 5091, "time": 875, "level": 16}, {"ability": 5093, "time": 1039, "level": 17}, {"ability": 6235, "time": 1129, "level": 18}, {"ability": 6191, "time": 1634, "level": 19}], "hero_name": "Death Prophet", "item_0_name": "Shiva's Guard", "item_1_name": "Phase Boots", "item_2_name": "Eul's Scepter of Divinity", "item_4_name": "Null Talisman", "item_5_name": "Linken's Sphere", "leaver_status_name": "NONE", "leaver_status_description": "finished match, no abandon"}, {"account_id": 4294967295, "player_slot": 3, "hero_id": 74, "item_0": 108, "item_1": 48, "item_2": 41, "item_3": 65, "item_4": 273, "item_5": 123, "backpack_0": 0, "backpack_1": 0, "backpack_2": 0, "kills": 3, "deaths": 3, "assists": 11, "leaver_status": 0, "last_hits": 66, "denies": 3, "gold_per_min": 764, "xp_per_min": 1156, "level": 25, "hero_damage": 12107, "tower_damage": 1780, "hero_healing": 365, "gold": 2114, "gold_spent": 19690, "scaled_hero_damage": 4432, "scaled_tower_damage": 1197, "scaled_hero_healing": 252, "ability_upgrades": [{"ability": 5370, "time": 98, "level": 1}, {"ability": 5372, "time": 200, "level": 2}, {"ability": 5372, "time": 245, "level": 3}, {"ability": 5371, "time": 376, "level": 4}, {"ability": 5370, "time": 413, "level": 5}, {"ability": 5372, "time": 455, "level": 6}, {"ability": 5371, "time": 508, "level": 7}, {"ability": 5370, "time": 611, "level": 8}, {"ability": 5372, "time": 637, "level": 9}, {"ability": 6811, "time": 737, "level": 10}, {"ability": 5371, "time": 739, "level": 11}, {"ability": 5370, "time": 751, "level": 12}, {"ability": 5372, "time": 797, "level": 13}, {"ability": 5371, "time": 811, "level": 14}, {"ability": 7148, "time": 893, "level": 15}, {"ability": 5370, "time": 1010, "level": 16}, {"ability": 5372, "time": 1051, "level": 17}, {"ability": 5371, "time": 1096, "level": 18}, {"ability": 5370, "time": 1124, "level": 19}, {"ability": 6656, "time": 1181, "level": 20}, {"ability": 5372, "time": 1262, "level": 21}, {"ability": 5371, "time": 1365, "level": 22}, {"ability": 5370, "time": 1542, "level": 23}, {"ability": 5371, "time": 1550, "level": 24}, {"ability": 6098, "time": 1558, "level": 25}], "hero_name": "Invoker", "item_0_name": "Aghanim's Scepter", "item_1_name": "Boots of Travel", "item_2_name": "Bottle", "item_3_name": "Hand of Midas", "item_5_name": "Linken's Sphere", "leaver_status_name": "NONE", "leaver_status_description": "finished match, no abandon"}, {"account_id": 369636750, "player_slot": 4, "hero_id": 26, "item_0": 204, "item_1": 249, "item_2": 40, "item_3": 108, "item_4": 232, "item_5": 214, "backpack_0": 259, "backpack_1": 0, "backpack_2": 0, "kills": 12, "deaths": 7, "assists": 3, "leaver_status": 0, "last_hits": 45, "denies": 4, "gold_per_min": 870, "xp_per_min": 1221, "level": 25, "hero_damage": 21701, "tower_damage": 379, "hero_healing": 0, "gold": 442, "gold_spent": 24285, "scaled_hero_damage": 11390, "scaled_tower_damage": 260, "scaled_hero_healing": 0, "ability_upgrades": [{"ability": 5044, "time": 91, "level": 1}, {"ability": 5045, "time": 201, "level": 2}, {"ability": 5046, "time": 246, "level": 3}, {"ability": 5046, "time": 345, "level": 4}, {"ability": 5045, "time": 375, "level": 5}, {"ability": 5047, "time": 434, "level": 6}, {"ability": 5046, "time": 497, "level": 7}, {"ability": 5044, "time": 529, "level": 8}, {"ability": 5044, "time": 550, "level": 9}, {"ability": 5968, "time": 651, "level": 10}, {"ability": 5046, "time": 654, "level": 11}, {"ability": 5047, "time": 661, "level": 12}, {"ability": 5044, "time": 751, "level": 13}, {"ability": 5045, "time": 754, "level": 14}, {"ability": 6600, "time": 816, "level": 15}, {"ability": 5045, "time": 817, "level": 16}, {"ability": 5047, "time": 865, "level": 17}, {"ability": 6235, "time": 1140, "level": 18}, {"ability": 6678, "time": 1627, "level": 19}], "hero_name": "Lion", "item_0_name": "Dagon", "item_1_name": "Silver Edge", "item_2_name": "Dust of Appearance", "item_3_name": "Aghanim's Scepter", "item_4_name": "Aether Lens", "item_5_name": "Tranquil Boots", "leaver_status_name": "NONE", "leaver_status_description": "finished match, no abandon"}, {"account_id": 27927764, "player_slot": 128, "hero_id": 18, "item_0": 63, "item_1": 156, "item_2": 116, "item_3": 242, "item_4": 141, "item_5": 143, "backpack_0": 125, "backpack_1": 0, "backpack_2": 0, "kills": 11, "deaths": 4, "assists": 7, "leaver_status": 0, "last_hits": 77, "denies": 0, "gold_per_min": 1168, "xp_per_min": 1544, "level": 25, "hero_damage": 32446, "tower_damage": 2220, "hero_healing": 0, "gold": 990, "gold_spent": 33270, "scaled_hero_damage": 15760, "scaled_tower_damage": 957, "scaled_hero_healing": 0, "ability_upgrades": [{"ability": 5094, "time": 90, "level": 1}, {"ability": 5095, "time": 214, "level": 2}, {"ability": 5096, "time": 247, "level": 3}, {"ability": 5095, "time": 320, "level": 4}, {"ability": 5094, "time": 403, "level": 5}, {"ability": 5097, "time": 463, "level": 6}, {"ability": 5095, "time": 562, "level": 7}, {"ability": 5095, "time": 641, "level": 8}, {"ability": 5982, "time": 645, "level": 9}, {"ability": 5094, "time": 646, "level": 10}, {"ability": 5096, "time": 700, "level": 11}, {"ability": 5097, "time": 800, "level": 12}, {"ability": 5094, "time": 804, "level": 13}, {"ability": 5096, "time": 812, "level": 14}, {"ability": 6141, "time": 922, "level": 15}, {"ability": 5096, "time": 924, "level": 16}, {"ability": 5097, "time": 968, "level": 17}, {"ability": 6111, "time": 1039, "level": 18}, {"ability": 6910, "time": 1319, "level": 19}], "hero_name": "Sven", "item_0_name": "Power Treads", "item_1_name": "Satanic", "item_2_name": "Black King Bar", "item_3_name": "Crimson Guard", "item_4_name": "Daedalus", "item_5_name": "Skull Basher", "leaver_status_name": "NONE", "leaver_status_description": "finished match, no abandon"}, {"account_id": 4294967295, "player_slot": 129, "hero_id": 104, "item_0": 63, "item_1": 125, "item_2": 279, "item_3": 31, "item_4": 0, "item_5": 61, "backpack_0": 0, "backpack_1": 0, "backpack_2": 0, "kills": 0, "deaths": 4, "assists": 3, "leaver_status": 4, "last_hits": 35, "denies": 3, "gold_per_min": 504, "xp_per_min": 459, "level": 16, "hero_damage": 3559, "tower_damage": 0, "hero_healing": 0, "gold": 0, "gold_spent": 6780, "scaled_hero_damage": 2821, "scaled_tower_damage": 0, "scaled_hero_healing": 0, "ability_upgrades": [{"ability": 5597, "time": 89, "level": 1}, {"ability": 5596, "time": 214, "level": 2}, {"ability": 5597, "time": 247, "level": 3}, {"ability": 5596, "time": 335, "level": 4}, {"ability": 5597, "time": 394, "level": 5}, {"ability": 5598, "time": 461, "level": 6}, {"ability": 5595, "time": 511, "level": 7}, {"ability": 5595, "time": 552, "level": 8}, {"ability": 5595, "time": 651, "level": 9}, {"ability": 5987, "time": 693, "level": 10}, {"ability": 5595, "time": 724, "level": 11}, {"ability": 5598, "time": 735, "level": 12}, {"ability": 5596, "time": 736, "level": 13}, {"ability": 5596, "time": 856, "level": 14}, {"ability": 5907, "time": 878, "level": 15}, {"ability": 5597, "time": 925, "level": 16}], "hero_name": "Legion Commander", "item_0_name": "Power Treads", "item_1_name": "Vanguard", "item_3_name": "Cloak", "item_5_name": "Vitality Booster", "leaver_status_name": "AFK", "leaver_status_description": "player AFK, abandon"}, {"account_id": 4294967295, "player_slot": 130, "hero_id": 11, "item_0": 249, "item_1": 63, "item_2": 247, "item_3": 139, "item_4": 108, "item_5": 116, "backpack_0": 0, "backpack_1": 0, "backpack_2": 0, "kills": 7, "deaths": 6, "assists": 10, "leaver_status": 0, "last_hits": 117, "denies": 4, "gold_per_min": 1154, "xp_per_min": 1439, "level": 25, "hero_damage": 29134, "tower_damage": 2961, "hero_healing": 0, "gold": 1956, "gold_spent": 26235, "scaled_hero_damage": 15287, "scaled_tower_damage": 1868, "scaled_hero_healing": 0, "ability_upgrades": [{"ability": 5059, "time": 97, "level": 1}, {"ability": 5063, "time": 194, "level": 2}, {"ability": 5063, "time": 207, "level": 3}, {"ability": 5062, "time": 238, "level": 4}, {"ability": 5062, "time": 271, "level": 5}, {"ability": 5064, "time": 309, "level": 6}, {"ability": 5063, "time": 351, "level": 7}, {"ability": 5062, "time": 395, "level": 8}, {"ability": 5063, "time": 421, "level": 9}, {"ability": 5059, "time": 522, "level": 10}, {"ability": 5059, "time": 523, "level": 11}, {"ability": 5906, "time": 526, "level": 12}, {"ability": 5059, "time": 603, "level": 13}, {"ability": 5062, "time": 702, "level": 14}, {"ability": 5064, "time": 740, "level": 15}, {"ability": 6141, "time": 797, "level": 16}, {"ability": 5064, "time": 912, "level": 17}, {"ability": 6070, "time": 1034, "level": 18}, {"ability": 6445, "time": 1337, "level": 19}], "hero_name": "Shadow Fiend", "item_0_name": "Silver Edge", "item_1_name": "Power Treads", "item_2_name": "Moon Shard", "item_3_name": "Butterfly", "item_4_name": "Aghanim's Scepter", "item_5_name": "Black King Bar", "leaver_status_name": "NONE", "leaver_status_description": "finished match, no abandon"}, {"account_id": 4294967295, "player_slot": 131, "hero_id": 17, "item_0": 121, "item_1": 121, "item_2": 121, "item_3": 277, "item_4": 69, "item_5": 121, "backpack_0": 0, "backpack_1": 0, "backpack_2": 0, "kills": 6, "deaths": 3, "assists": 10, "leaver_status": 0, "last_hits": 145, "denies": 2, "gold_per_min": 1122, "xp_per_min": 1347, "level": 25, "hero_damage": 23847, "tower_damage": 638, "hero_healing": 0, "gold": 4610, "gold_spent": 27685, "scaled_hero_damage": 11637, "scaled_tower_damage": 304, "scaled_hero_healing": 0, "ability_upgrades": [{"ability": 5098, "time": 92, "level": 1}, {"ability": 5100, "time": 204, "level": 2}, {"ability": 5098, "time": 248, "level": 3}, {"ability": 5099, "time": 313, "level": 4}, {"ability": 5098, "time": 436, "level": 5}, {"ability": 5101, "time": 517, "level": 6}, {"ability": 5100, "time": 543, "level": 7}, {"ability": 5098, "time": 596, "level": 8}, {"ability": 5099, "time": 618, "level": 9}, {"ability": 6160, "time": 717, "level": 10}, {"ability": 5100, "time": 760, "level": 11}, {"ability": 5101, "time": 797, "level": 12}, {"ability": 5100, "time": 798, "level": 13}, {"ability": 5099, "time": 825, "level": 14}, {"ability": 6916, "time": 908, "level": 15}, {"ability": 5099, "time": 938, "level": 16}, {"ability": 5101, "time": 1109, "level": 17}, {"ability": 5907, "time": 1173, "level": 18}, {"ability": 6908, "time": 1394, "level": 19}], "hero_name": "Storm Spirit", "item_0_name": "Bloodstone", "item_1_name": "Bloodstone", "item_2_name": "Bloodstone", "item_4_name": "Perseverance", "item_5_name": "Bloodstone", "leaver_status_name": "NONE", "leaver_status_description": "finished match, no abandon"}, {"account_id": 377001375, "player_slot": 132, "hero_id": 38, "item_0": 249, "item_1": 112, "item_2": 194, "item_3": 50, "item_4": 69, "item_5": 90, "backpack_0": 0, "backpack_1": 0, "backpack_2": 0, "kills": 3, "deaths": 10, "assists": 10, "leaver_status": 0, "last_hits": 75, "denies": 2, "gold_per_min": 930, "xp_per_min": 1239, "level": 25, "hero_damage": 17897, "tower_damage": 6991, "hero_healing": 0, "gold": 3470, "gold_spent": 22975, "scaled_hero_damage": 11600, "scaled_tower_damage": 4104, "scaled_hero_healing": 0, "ability_upgrades": [{"ability": 7230, "time": 94, "level": 1}, {"ability": 5172, "time": 219, "level": 2}, {"ability": 7230, "time": 273, "level": 3}, {"ability": 5172, "time": 327, "level": 4}, {"ability": 5168, "time": 407, "level": 5}, {"ability": 5177, "time": 482, "level": 6}, {"ability": 7230, "time": 492, "level": 7}, {"ability": 7230, "time": 518, "level": 8}, {"ability": 5172, "time": 599, "level": 9}, {"ability": 5172, "time": 718, "level": 10}, {"ability": 5987, "time": 812, "level": 11}, {"ability": 5177, "time": 834, "level": 12}, {"ability": 5168, "time": 852, "level": 13}, {"ability": 5168, "time": 859, "level": 14}, {"ability": 6517, "time": 924, "level": 15}, {"ability": 5168, "time": 952, "level": 16}, {"ability": 5177, "time": 1044, "level": 17}, {"ability": 6235, "time": 1048, "level": 18}, {"ability": 6612, "time": 1454, "level": 19}], "hero_name": "Beastmaster", "item_0_name": "Silver Edge", "item_1_name": "Assault Cuirass", "item_2_name": "Necronomicon", "item_3_name": "Phase Boots", "item_4_name": "Perseverance", "item_5_name": "Pipe of Insight", "leaver_status_name": "NONE", "leaver_status_description": "finished match, no abandon"}], "radiant_win": false, "duration": 1652, "pre_game_duration": 60, "start_time": 1548125288, "match_id": 4352014231, "match_seq_num": 3770798959, "tower_status_radiant": 0, "tower_status_dire": 1926, "barracks_status_radiant": 48, "barracks_status_dire": 51, "cluster": 136, "first_blood_time": 162, "lobby_type": 0, "human_players": 10, "leagueid": 0, "positive_votes": 0, "negative_votes": 0, "game_mode": 23, "flags": 1, "engine": 1, "radiant_score": 27, "dire_score": 28, "picks_bans": [{"is_pick": false, "hero_id": 14, "team": 0, "order": 0}, {"is_pick": false, "hero_id": 105, "team": 0, "order": 1}, {"is_pick": false, "hero_id": 35, "team": 0, "order": 2}, {"is_pick": false, "hero_id": 44, "team": 0, "order": 3}, {"is_pick": false, "hero_id": 99, "team": 0, "order": 4}, {"is_pick": false, "hero_id": 95, "team": 1, "order": 5}, {"is_pick": false, "hero_id": 58, "team": 1, "order": 6}, {"is_pick": false, "hero_id": 32, "team": 1, "order": 7}], "lobby_name": "Public matchmaking", "cluster_name": "Europe West"}