{"players": [{"account_id": 4294967295, "player_slot": 0, "hero_id": 70, "item_0": 50, "item_1": 152, "item_2": 127, "item_3": 81, "item_4": 143, "item_5": 0, "backpack_0": 0, "backpack_1": 0, "backpack_2": 0, "kills": 2, "deaths": 6, "assists": 6, "leaver_status": 0, "last_hits": 51, "denies": 0, "gold_per_min": 795, "xp_per_min": 1163, "level": 23, "hero_damage": 5757, "tower_damage": 6292, "hero_healing": 1394, "gold": 5416, "gold_spent": 12015, "scaled_hero_damage": 3621, "scaled_tower_damage": 3674, "scaled_hero_healing": 501, "ability_upgrades": [{"ability": 5359, "time": 138, "level": 1}, {"ability": 5358, "time": 237, "level": 2}, {"ability": 5357, "time": 328, "level": 3}, {"ability": 5358, "time": 389, "level": 4}, {"ability": 5359, "time": 536, "level": 5}, {"ability": 5360, "time": 595, "level": 6}, {"ability": 5358, "time": 666, "level": 7}, {"ability": 5358, "time": 720, "level": 8}, {"ability": 5359, "time": 741, "level": 9}, {"ability": 5359, "time": 778, "level": 10}, {"ability": 5357, "time": 843, "level": 11}, {"ability": 5360, "time": 851, "level": 12}, {"ability": 5982, "time": 922, "level": 13}, {"ability": 5357, "time": 959, "level": 14}, {"ability": 5357, "time": 961, "level": 15}, {"ability": 6170, "time": 1021, "level": 16}, {"ability": 5360, "time": 1072, "level": 17}, {"ability": 6132, "time": 1215, "level": 18}], "hero_name": "Ursa", "item_0_name": "Phase Boots", "item_1_name": "Shadow Blade", "item_2_name": "Blade Mail", "item_3_name": "Vladmir's Offering", "item_4_name": "Skull Basher", "leaver_status_name": "NONE", "leaver_status_description": "finished match, no abandon"}, {"account_id": 4294967295, "player_slot": 1, "hero_id": 27, "item_0": 63, "item_1": 0, "item_2": 216, "item_3": 108, "item_4": 277, "item_5": 0, "backpack_0": 0, "backpack_1": 0, "backpack_2": 0, "kills": 0, "deaths": 7, "assists": 5, "leaver_status": 0, "last_hits": 51, "denies": 1, "gold_per_min": 705, "xp_per_min": 1284, "level": 24, "hero_damage": 2935, "tower_damage": 2628, "hero_healing": 0, "gold": 4566, "gold_spent": 11145, "scaled_hero_damage": 1403, "scaled_tower_damage": 1577, "scaled_hero_healing": 0, "ability_upgrades": [{"ability": 5080, "time": 133, "level": 1}, {"ability": 5078, "time": 251, "level": 2}, {"ability": 5078, "time": 291, "level": 3}, {"ability": 5079, "time": 351, "level": 4}, {"ability": 5080, "time": 597, "level": 5}, {"ability": 5081, "time": 653, "level": 6}, {"ability": 5078, "time": 692, "level": 7}, {"ability": 5078, "time": 753, "level": 8}, {"ability": 6017, "time": 840, "level": 9}, {"ability": 5079, "time": 842, "level": 10}, {"ability": 5080, "time": 886, "level": 11}, {"ability": 5081, "time": 903, "level": 12}, {"ability": 5079, "time": 911, "level": 13}, {"ability": 5080, "time": 933, "level": 14}, {"ability": 6877, "time": 1017, "level": 15}, {"ability": 5079, "time": 1028, "level": 16}, {"ability": 5081, "time": 1141, "level": 17}, {"ability": 6295, "time": 1207, "level": 18}], "hero_name": "Shadow Shaman", "item_0_name": "Power Treads", "item_2_name": "Enchanted Mango", "item_3_name": "Aghanim's Scepter", "leaver_status_name": "NONE", "leaver_status_description": "finished match, no abandon"}, {"account_id": 4294967295, "player_slot": 2, "hero_id": 111, "item_0": 204, "item_1": 48, "item_2": 232, "item_3": 41, "item_4": 0, "item_5": 0, "backpack_0": 0, "backpack_1": 0, "backpack_2": 0, "kills": 7, "deaths": 2, "assists": 6, "leaver_status": 0, "last_hits": 30, "denies": 0, "gold_per_min": 892, "xp_per_min": 1464, "level": 25, "hero_damage": 6318, "tower_damage": 116, "hero_healing": 6385, "gold": 5107, "gold_spent": 14970, "scaled_hero_damage": 6511, "scaled_tower_damage": 54, "scaled_hero_healing": 2009, "ability_upgrades": [{"ability": 5639, "time": 182, "level": 1}, {"ability": 5638, "time": 242, "level": 2}, {"ability": 5639, "time": 259, "level": 3}, {"ability": 5637, "time": 297, "level": 4}, {"ability": 5639, "time": 322, "level": 5}, {"ability": 5640, "time": 370, "level": 6}, {"ability": 5639, "time": 422, "level": 7}, {"ability": 5638, "time": 447, "level": 8}, {"ability": 5638, "time": 465, "level": 9}, {"ability": 6540, "time": 542, "level": 10}, {"ability": 5638, "time": 604, "level": 11}, {"ability": 5640, "time": 688, "level": 12}, {"ability": 5637, "time": 708, "level": 13}, {"ability": 5637, "time": 921, "level": 14}, {"ability": 6056, "time": 987, "level": 15}, {"ability": 5640, "time": 1021, "level": 16}, {"ability": 5637, "time": 1051, "level": 17}, {"ability": 6970, "time": 1126, "level": 18}, {"ability": 6206, "time": 1396, "level": 19}], "hero_name": "Oracle", "item_0_name": "Dagon", "item_1_name": "Boots of Travel", "item_2_name": "Aether Lens", "item_3_name": "Bottle", "leaver_status_name": "NONE", "leaver_status_description": "finished match, no abandon"}, {"account_id": 4294967295, "player_slot": 3, "hero_id": 8, "item_0": 50, "item_1": 0, "item_2": 145, "item_3": 108, "item_4": 247, "item_5": 0, "backpack_0": 0, "backpack_1": 0, "backpack_2": 0, "kills": 3, "deaths": 5, "assists": 7, "leaver_status": 0, "last_hits": 52, "denies": 3, "gold_per_min": 856, "xp_per_min": 1500, "level": 25, "hero_damage": 6385, "tower_damage": 3118, "hero_healing": 3615, "gold": 3890, "gold_spent": 14725, "scaled_hero_damage": 3922, "scaled_tower_damage": 1627, "scaled_hero_healing": 1344, "ability_upgrades": [{"ability": 5028, "time": 134, "level": 1}, {"ability": 5027, "time": 237, "level": 2}, {"ability": 5028, "time": 328, "level": 3}, {"ability": 5027, "time": 394, "level": 4}, {"ability": 5028, "time": 537, "level": 5}, {"ability": 5030, "time": 577, "level": 6}, {"ability": 5028, "time": 674, "level": 7}, {"ability": 5027, "time": 712, "level": 8}, {"ability": 5027, "time": 734, "level": 9}, {"ability": 5918, "time": 843, "level": 10}, {"ability": 5029, "time": 854, "level": 11}, {"ability": 5030, "time": 921, "level": 12}, {"ability": 5029, "time": 944, "level": 13}, {"ability": 5029, "time": 958, "level": 14}, {"ability": 5906, "time": 1000, "level": 15}, {"ability": 5029, "time": 1108, "level": 16}, {"ability": 5030, "time": 1126, "level": 17}, {"ability": 7021, "time": 1135, "level": 18}, {"ability": 6662, "time": 1320, "level": 19}], "hero_name": "Juggernaut", "item_0_name": "Phase Boots", "item_2_name": "Battle Fury", "item_3_name": "Aghanim's Scepter", "item_4_name": "Moon Shard", "leaver_status_name": "NONE", "leaver_status_description": "finished match, no abandon"}, {"account_id": 4294967295, "player_slot": 4, "hero_id": 44, "item_0": 168, "item_1": 50, "item_2": 116, "item_3": 143, "item_4": 135, "item_5": 114, "backpack_0": 0, "backpack_1": 0, "backpack_2": 0, "kills": 19, "deaths": 3, "assists": 11, "leaver_status": 0, "last_hits": 56, "denies": 4, "gold_per_min": 1461, "xp_per_min": 1855, "level": 25, "hero_damage": 49559, "tower_damage": 1732, "hero_healing": 0, "gold": 5464, "gold_spent": 26120, "scaled_hero_damage": 25475, "scaled_tower_damage": 1018, "scaled_hero_healing": 0, "ability_upgrades": [{"ability": 5192, "time": 134, "level": 1}, {"ability": 5190, "time": 253, "level": 2}, {"ability": 5191, "time": 292, "level": 3}, {"ability": 5192, "time": 351, "level": 4}, {"ability": 5192, "time": 423, "level": 5}, {"ability": 5193, "time": 459, "level": 6}, {"ability": 5191, "time": 568, "level": 7}, {"ability": 5191, "time": 569, "level": 8}, {"ability": 5191, "time": 618, "level": 9}, {"ability": 5938, "time": 691, "level": 10}, {"ability": 5190, "time": 745, "level": 11}, {"ability": 5193, "time": 875, "level": 12}, {"ability": 5192, "time": 877, "level": 13}, {"ability": 5190, "time": 878, "level": 14}, {"ability": 6289, "time": 923, "level": 15}, {"ability": 5193, "time": 958, "level": 16}, {"ability": 5190, "time": 959, "level": 17}, {"ability": 7011, "time": 1023, "level": 18}, {"ability": 6192, "time": 1108, "level": 19}], "hero_name": "Phantom Assassin", "item_0_name": "Desolator", "item_1_name": "Phase Boots", "item_2_name": "Black King Bar", "item_3_name": "Skull Basher", "item_4_name": "Monkey King Bar", "item_5_name": "Heart of Tarrasque", "leaver_status_name": "NONE", "leaver_status_description": "finished match, no abandon"}, {"account_id": 4294967295, "player_slot": 128, "hero_id": 2, "item_0": 214, "item_1": 242, "item_2": 1, "item_3": 127, "item_4": 36, "item_5": 116, "backpack_0": 0, "backpack_1": 0, "backpack_2": 0, "kills": 7, "deaths": 5, "assists": 8, "leaver_status": 0, "last_hits": 49, "denies": 11, "gold_per_min": 829, "xp_per_min": 970, "level": 21, "hero_damage": 19554, "tower_damage": 141, "hero_healing": 0, "gold": 3519, "gold_spent": 14590, "scaled_hero_damage": 14243, "scaled_tower_damage": 46, "scaled_hero_healing": 0, "ability_upgrades": [{"ability": 5008, "time": 180, "level": 1}, {"ability": 5009, "time": 250, "level": 2}, {"ability": 5009, "time": 270, "level": 3}, {"ability": 5008, "time": 296, "level": 4}, {"ability": 5009, "time": 339, "level": 5}, {"ability": 5010, "time": 354, "level": 6}, {"ability": 5009, "time": 423, "level": 7}, {"ability": 5007, "time": 477, "level": 8}, {"ability": 5008, "time": 524, "level": 9}, {"ability": 5982, "time": 546, "level": 10}, {"ability": 5007, "time": 590, "level": 11}, {"ability": 5010, "time": 646, "level": 12}, {"ability": 5007, "time": 680, "level": 13}, {"ability": 5007, "time": 746, "level": 14}, {"ability": 6141, "time": 842, "level": 15}, {"ability": 5008, "time": 853, "level": 16}, {"ability": 5010, "time": 907, "level": 17}, {"ability": 6308, "time": 1018, "level": 18}], "hero_name": "Axe", "item_0_name": "Tranquil Boots", "item_1_name": "Crimson Guard", "item_2_name": "Blink Dagger", "item_3_name": "Blade Mail", "item_4_name": "Magic Wand", "item_5_name": "Black King Bar", "leaver_status_name": "NONE", "leaver_status_description": "finished match, no abandon"}, {"account_id": 4294967295, "player_slot": 129, "hero_id": 58, "item_0": 2, "item_1": 43, "item_2": 168, "item_3": 10, "item_4": 14, "item_5": 0, "backpack_0": 0, "backpack_1": 0, "backpack_2": 0, "kills": 0, "deaths": 8, "assists": 3, "leaver_status": 2, "last_hits": 8, "denies": 0, "gold_per_min": 296, "xp_per_min": 497, "level": 15, "hero_damage": 1420, "tower_damage": 367, "hero_healing": 393, "gold": 2, "gold_spent": 5140, "scaled_hero_damage": 900, "scaled_tower_damage": 206, "scaled_hero_healing": 296, "ability_upgrades": [{"ability": 5269, "time": 190, "level": 1}, {"ability": 5267, "time": 327, "level": 2}, {"ability": 5268, "time": 348, "level": 3}, {"ability": 5269, "time": 445, "level": 4}, {"ability": 5269, "time": 573, "level": 5}, {"ability": 5270, "time": 587, "level": 6}, {"ability": 5269, "time": 615, "level": 7}, {"ability": 5267, "time": 676, "level": 8}, {"ability": 5268, "time": 797, "level": 9}, {"ability": 5268, "time": 814, "level": 10}, {"ability": 5270, "time": 855, "level": 11}, {"ability": 5268, "time": 863, "level": 12}, {"ability": 5267, "time": 869, "level": 13}, {"ability": 5267, "time": 987, "level": 14}], "hero_name": "Enchantress", "item_0_name": "Blades of Attack", "item_1_name": "Sentry Ward", "item_2_name": "Desolator", "item_3_name": "Quarterstaff", "item_4_name": "Slippers of Agility", "leaver_status_name": "DISCONNECTED_TOO_LONG", "leaver_status_description": "player DC > 5min, abandon"}, {"account_id": 4294967295, "player_slot": 130, "hero_id": 101, "item_0": 180, "item_1": 152, "item_2": 206, "item_3": 77, "item_4": 259, "item_5": 77, "backpack_0": 0, "backpack_1": 0, "backpack_2": 0, "kills": 8, "deaths": 4, "assists": 7, "leaver_status": 1, "last_hits": 39, "denies": 5, "gold_per_min": 721, "xp_per_min": 1269, "level": 24, "hero_damage": 18118, "tower_damage": 0, "hero_healing": 0, "gold": 2, "gold_spent": 10590, "scaled_hero_damage": 12444, "scaled_tower_damage": 0, "scaled_hero_healing": 0, "ability_upgrades": [{"ability": 5581, "time": 210, "level": 1}, {"ability": 5582, "time": 238, "level": 2}, {"ability": 5581, "time": 259, "level": 3}, {"ability": 5582, "time": 295, "level": 4}, {"ability": 5581, "time": 349, "level": 5}, {"ability": 5584, "time": 437, "level": 6}, {"ability": 5583, "time": 510, "level": 7}, {"ability": 5581, "time": 598, "level": 8}, {"ability": 5583, "time": 648, "level": 9}, {"ability": 5925, "time": 687, "level": 10}, {"ability": 5583, "time": 736, "level": 11}, {"ability": 5583, "time": 788, "level": 12}, {"ability": 5582, "time": 816, "level": 13}, {"ability": 5582, "time": 858, "level": 14}, {"ability": 5584, "time": 877, "level": 15}, {"ability": 6181, "time": 1027, "level": 16}, {"ability": 5584, "time": 1080, "level": 17}, {"ability": 6885, "time": 1198, "level": 18}], "hero_name": "Skywrath Mage", "item_0_name": "Arcane Boots", "item_1_name": "Shadow Blade", "item_2_name": "Rod of Atos", "item_3_name": "Null Talisman", "item_5_name": "Null Talisman", "leaver_status_name": "DISCONNECTED", "leaver_status_description": "player DC, no abandon"}, {"account_id": 4294967295, "player_slot": 131, "hero_id": 21, "item_0": 250, "item_1": 108, "item_2": 0, "item_3": 15, "item_4": 214, "item_5": 0, "backpack_0": 0, "backpack_1": 0, "backpack_2": 0, "kills": 4, "deaths": 7, "assists": 3, "leaver_status": 0, "last_hits": 60, "denies": 2, "gold_per_min": 883, "xp_per_min": 1400, "level": 25, "hero_damage": 9541, "tower_damage": 1875, "hero_healing": 0, "gold": 6138, "gold_spent": 13070, "scaled_hero_damage": 6774, "scaled_tower_damage": 1113, "scaled_hero_healing": 0, "ability_upgrades": [{"ability": 5131, "time": 138, "level": 1}, {"ability": 5132, "time": 282, "level": 2}, {"ability": 5131, "time": 300, "level": 3}, {"ability": 5130, "time": 340, "level": 4}, {"ability": 5131, "time": 410, "level": 5}, {"ability": 5133, "time": 485, "level": 6}, {"ability": 5131, "time": 563, "level": 7}, {"ability": 5130, "time": 623, "level": 8}, {"ability": 5130, "time": 725, "level": 9}, {"ability": 6413, "time": 775, "level": 10}, {"ability": 5130, "time": 827, "level": 11}, {"ability": 5133, "time": 909, "level": 12}, {"ability": 5944, "time": 971, "level": 13}, {"ability": 5132, "time": 976, "level": 14}, {"ability": 5132, "time": 978, "level": 15}, {"ability": 5132, "time": 979, "level": 16}, {"ability": 5133, "time": 1107, "level": 17}, {"ability": 6144, "time": 1266, "level": 18}], "hero_name": "Windranger", "item_0_name": "Bloodthorn", "item_1_name": "Aghanim's Scepter", "item_3_name": "Mantle of Intelligence", "item_4_name": "Tranquil Boots", "leaver_status_name": "NONE", "leaver_status_description": "finished match, no abandon"}, {"account_id": 64989974, "player_slot": 132, "hero_id": 53, "item_0": 168, "item_1": 63, "item_2": 152, "item_3": 241, "item_4": 241, "item_5": 81, "backpack_0": 0, "backpack_1": 0, "backpack_2": 0, "kills": 1, "deaths": 8, "assists": 9, "leaver_status": 0, "last_hits": 52, "denies": 8, "gold_per_min": 676, "xp_per_min": 855, "level": 20, "hero_damage": 6007, "tower_damage": 1361, "hero_healing": 323, "gold": 4752, "gold_spent": 10825, "scaled_hero_damage": 3818, "scaled_tower_damage": 792, "scaled_hero_healing": 147, "ability_upgrades": [{"ability": 5245, "time": 181, "level": 1}, {"ability": 5246, "time": 275, "level": 2}, {"ability": 5247, "time": 340, "level": 3}, {"ability": 5247, "time": 383, "level": 4}, {"ability": 5245, "time": 449, "level": 5}, {"ability": 5248, "time": 514, "level": 6}, {"ability": 5246, "time": 558, "level": 7}, {"ability": 5246, "time": 612, "level": 8}, {"ability": 5246, "time": 703, "level": 9}, {"ability": 5939, "time": 751, "level": 10}, {"ability": 5245, "time": 781, "level": 11}, {"ability": 5247, "time": 837, "level": 12}, {"ability": 5245, "time": 1057, "level": 13}, {"ability": 5247, "time": 1074, "level": 14}, {"ability": 6500, "time": 1078, "level": 15}, {"ability": 5248, "time": 1082, "level": 16}, {"ability": 5248, "time": 1159, "level": 17}, {"ability": 6210, "time": 1218, "level": 18}], "hero_name": "Nature's Prophet", "item_0_name": "Desolator", "item_1_name": "Power Treads", "item_2_name": "Shadow Blade", "item_3_name": "Tango (Shared)", "item_4_name": "Tango (Shared)", "item_5_name": "Vladmir's Offering", "leaver_status_name": "NONE", "leaver_status_description": "finished match, no abandon"}], "radiant_win": true, "duration": 1262, "pre_game_duration": 60, "start_time": 1549502517, "match_id": 4397576978, "match_seq_num": 3801947992, "tower_status_radiant": 1830, "tower_status_dire": 416, "barracks_status_radiant": 63, "barracks_status_dire": 60, "cluster": 135, "first_blood_time": 162, "lobby_type": 0, "human_players": 10, "leagueid": 0, "positive_votes": 0, "negative_votes": 0, "game_mode": 23, "flags": 1, "engine": 1, "radiant_score": 32, "dire_score": 23, "picks_bans": [{"is_pick": false, "hero_id": 1, "team": 0, "order": 0}, {"is_pick": false, "hero_id": 12, "team": 0, "order": 1}, {"is_pick": false, "hero_id": 74, "team": 0, "order": 2}, {"is_pick": false, "hero_id": 26, "team": 0, "order": 3}, {"is_pick": false, "hero_id": 99, "team": 0, "order": 4}, {"is_pick": false, "hero_id": 105, "team": 1, "order": 5}], "lobby_name": "Public matchmaking", "cluster_name": "Europe West"}